LICENSE
README.md
setup.py
tastyigniter/__init__.py
tastyigniter.egg-info/PKG-INFO
tastyigniter.egg-info/SOURCES.txt
tastyigniter.egg-info/dependency_links.txt
tastyigniter.egg-info/top_level.txt