Metadata-Version: 2.1
Name: tastyigniter
Version: 0.0.6
Summary: Async Python wrapper for TastyIgniter APIs (v26.beta)
Home-page: https://github.com/djtimca/tastyigniter-api
Author: Tim Empringham
Author-email: tim.empringham@live.ca
License: UNKNOWN
Keywords: TastyIgniter
Platform: UNKNOWN
Classifier: Programming Language :: Python :: 3
Classifier: License :: OSI Approved :: MIT License
Classifier: Operating System :: OS Independent
License-File: LICENSE
